{
  "name": "assorteddiscoveries:nether_cabin/warped_forest/front_porches",
  "fallback": "minecraft:empty",
  "elements": [
    {
      "weight": 1,
      "element": {
        "element_type": "minecraft:single_pool_element",
        "location": "assorteddiscoveries:nether_cabin/warped_forest/front_porches/warped_forest_front_porch",
        "processors": "minecraft:empty",
		"_comment1": "The projection has to be rigid or the porch won't spawn with the cabin.",
        "projection": "rigid"
      }
    }
  ]
}